autobex/__init__.py
autobex/excluded_tags.txt
autobex/osm_search_plus.py
autobex/tags.txt
autobex-0.1.162.dist-info/licenses/LICENSE
autobex-0.1.162.dist-info/METADATA
autobex-0.1.162.dist-info/WHEEL
autobex-0.1.162.dist-info/top_level.txt
autobex-0.1.162.dist-info/RECORD
